rsi_divergence/__init__.py
rsi_divergence/cli.py
rsi_divergence/core.py
rsi_divergence/utils.py
rsi_divergence_detector-0.1.0.dist-info/LICENSE
rsi_divergence_detector-0.1.0.dist-info/METADATA
rsi_divergence_detector-0.1.0.dist-info/WHEEL
rsi_divergence_detector-0.1.0.dist-info/entry_points.txt
rsi_divergence_detector-0.1.0.dist-info/RECORD
