Metadata-Version: 2.3
Name: rsi-divergence-detector
Version: 0.1.0
Summary: A tool to detect RSI divergences in price data.
License: BSD-3-Clause
Keywords: rsi,divergence,finance,trading,technical-analysis
Author: Tomi Šeregi
Requires-Python: >=3.9,<3.14
Classifier: Development Status :: 4 - Beta
Classifier: Intended Audience :: Developers
Classifier: Intended Audience :: Financial and Insurance Industry
Classifier: License :: OSI Approved :: BSD License
Classifier: License :: OSI Approved :: MIT License
Classifier: Programming Language :: Python :: 3
Classifier: Programming Language :: Python :: 3.9
Classifier: Programming Language :: Python :: 3.10
Classifier: Programming Language :: Python :: 3.11
Classifier: Programming Language :: Python :: 3.12
Classifier: Programming Language :: Python :: 3.13
Classifier: Topic :: Office/Business :: Financial :: Investment
Classifier: Topic :: Scientific/Engineering :: Mathematics
Requires-Dist: numpy (>=1.26)
Requires-Dist: pandas (>=2.2.3)
Requires-Dist: scipy (>=1.13)
Requires-Dist: typer[all] (>=0.9.0,<0.10.0)
Project-URL: Repository, https://github.com/AKzar1el/rsi_divergence_detector
